poker/__init__.py
poker/poker.py
poker_simple-0.0.1.dist-info/LICENSE
poker_simple-0.0.1.dist-info/METADATA
poker_simple-0.0.1.dist-info/WHEEL
poker_simple-0.0.1.dist-info/top_level.txt
poker_simple-0.0.1.dist-info/RECORD
