Metadata-Version: 2.1
Name: poker-simple
Version: 0.0.1
Summary: Poker problem utils.
Home-page: https://github.com/devgum/poker
Author: Devgum
Author-email: devgum@foxmail.com
License: UNKNOWN
Platform: UNKNOWN
Classifier: Programming Language :: Python :: 3.6
Classifier: License :: OSI Approved :: MIT License
Classifier: Operating System :: OS Independent
Requires-Python: >=3.6.0
